{"displayFieldName":"name","fieldAliases":{"OBJECTID":"OBJECTID","name":"Name","source":"Source"},"geometryType":"esriGeometryPoint","spatialReference":{"wkid":4326,"latestWkid":4326},"fields":[{"name":"OBJECTID","type":"esriFieldTypeOID","alias":"OBJECTID"},{"name":"name","type":"esriFieldTypeString","alias":"Name","length":254},{"name":"source","type":"esriFieldTypeString","alias":"Source","length":50}],"features":[{"attributes":{"OBJECTID":1,"name":" ","source":" Captain Segulls Fishing Charts 2007"},"geometry":{"x":-80.6124833338012,"y":30.840833333148765}},{"attributes":{"OBJECTID":2,"name":" ","source":" Captain Segulls Fishing Charts 2007"},"geometry":{"x":-80.6124833338012,"y":30.840833333148765}},{"attributes":{"OBJECTID":3,"name":" ","source":" Captain Segulls Fishing Charts 2007"},"geometry":{"x":-80.6124833338012,"y":30.840833333148765}},{"attributes":{"OBJECTID":4,"name":" ","source":" Captain Segulls Fishing Charts 2007"},"geometry":{"x":-80.69866666640209,"y":30.86191666659955}},{"attributes":{"OBJECTID":5,"name":" ","source":" Captain Segulls Fishing Charts 2007"},"geometry":{"x":-80.69866666640209,"y":30.86191666659955}},{"attributes":{"OBJECTID":6,"name":" ","source":" Captain Segulls Fishing Charts 2007"},"geometry":{"x":-80.69866666640209,"y":30.86191666659955}},{"attributes":{"OBJECTID":7,"name":" ","source":" Captain Segulls Fishing Charts 2007"},"geometry":{"x":-80.62748333324512,"y":30.89250000005763}},{"attributes":{"OBJECTID":8,"name":" ","source":" Captain Segulls Fishing Charts 2007"},"geometry":{"x":-80.62748333324512,"y":30.89250000005763}},{"attributes":{"OBJECTID":9,"name":" ","source":" Captain Segulls Fishing Charts 2007"},"geometry":{"x":-80.62748333324512,"y":30.89250000005763}},{"attributes":{"OBJECTID":10,"name":" ","source":" Captain Segulls Fishing Charts 2007"},"geometry":{"x":-80.70249999960332,"y":30.903500000081394}},{"attributes":{"OBJECTID":11,"name":" ","source":" Captain Segulls Fishing Charts 2007"},"geometry":{"x":-80.70249999960332,"y":30.903500000081394}},{"attributes":{"OBJECTID":12,"name":" ","source":" Captain Segulls Fishing Charts 2007"},"geometry":{"x":-80.70249999960332,"y":30.903500000081394}},{"attributes":{"OBJECTID":13,"name":" ","source":" Captain Segulls Fishing Charts 2007"},"geometry":{"x":-80.5915833325218,"y":30.913000000353758}},{"attributes":{"OBJECTID":14,"name":" ","source":" Captain Segulls Fishing Charts 2007"},"geometry":{"x":-80.5915833325218,"y":30.913000000353758}},{"attributes":{"OBJECTID":15,"name":" ","source":" Captain Segulls Fishing Charts 2007"},"geometry":{"x":-80.5915833325218,"y":30.913000000353758}},{"attributes":{"OBJECTID":16,"name":" ","source":" Captain Segulls Fishing Charts 2007"},"geometry":{"x":-80.51683333285234,"y":31.1358333330652}},{"attributes":{"OBJECTID":17,"name":" ","source":" Captain Segulls Fishing Charts 2007"},"geometry":{"x":-80.51683333285234,"y":31.1358333330652}},{"attributes":{"OBJECTID":18,"name":" ","source":" Captain Segulls Fishing Charts 2007"},"geometry":{"x":-80.51683333285234,"y":31.1358333330652}},{"attributes":{"OBJECTID":19,"name":" ","source":" Captain Segulls Fishing Charts 2007"},"geometry":{"x":-80.31483333411217,"y":31.37494999995065}},{"attributes":{"OBJECTID":20,"name":" ","source":" Captain Segulls Fishing Charts 2007"},"geometry":{"x":-80.31483333411217,"y":31.37494999995065}},{"attributes":{"OBJECTID":21,"name":" ","source":" Captain Segulls Fishing Charts 2007"},"geometry":{"x":-80.31483333411217,"y":31.37494999995065}},{"attributes":{"OBJECTID":22,"name":" ","source":" Captain Segulls Fishing Charts 2007"},"geometry":{"x":-80.33350000052603,"y":31.429166666524583}},{"attributes":{"OBJECTID":23,"name":" ","source":" Captain Segulls Fishing Charts 2007"},"geometry":{"x":-80.33350000052603,"y":31.429166666524583}},{"attributes":{"OBJECTID":24,"name":" ","source":" Captain Segulls Fishing Charts 2007"},"geometry":{"x":-80.33350000052603,"y":31.429166666524583}},{"attributes":{"OBJECTID":25,"name":" ","source":" Captain Segulls Fishing Charts 2007"},"geometry":{"x":-80.62916666649312,"y":31.445833333290466}},{"attributes":{"OBJECTID":26,"name":" ","source":" Captain Segulls Fishing Charts 2007"},"geometry":{"x":-80.62916666649312,"y":31.445833333290466}},{"attributes":{"OBJECTID":27,"name":" ","source":" Captain Segulls Fishing Charts 2007"},"geometry":{"x":-80.62916666649312,"y":31.445833333290466}},{"attributes":{"OBJECTID":28,"name":" ","source":" Captain Segulls Fishing Charts 2007"},"geometry":{"x":-80.35349999948521,"y":31.4708333329261}},{"attributes":{"OBJECTID":29,"name":" ","source":" Captain Segulls Fishing Charts 2007"},"geometry":{"x":-80.35349999948521,"y":31.4708333329261}},{"attributes":{"OBJECTID":30,"name":" ","source":" Captain Segulls Fishing Charts 2007"},"geometry":{"x":-80.35349999948521,"y":31.4708333329261}},{"attributes":{"OBJECTID":31,"name":" ","source":" Captain Segulls Fishing Charts 2007"},"geometry":{"x":-80.39516666690297,"y":31.549966666858975}},{"attributes":{"OBJECTID":32,"name":" ","source":" Captain Segulls Fishing Charts 2007"},"geometry":{"x":-80.39516666690297,"y":31.549966666858975}},{"attributes":{"OBJECTID":33,"name":" ","source":" Captain Segulls Fishing Charts 2007"},"geometry":{"x":-80.39516666690297,"y":31.549966666858975}},{"attributes":{"OBJECTID":34,"name":" ","source":" Captain Segulls Fishing Charts 2007"},"geometry":{"x":-80.41249999987325,"y":31.608316666700354}},{"attributes":{"OBJECTID":35,"name":" ","source":" Captain Segulls Fishing Charts 2007"},"geometry":{"x":-80.41249999987325,"y":31.608316666700354}},{"attributes":{"OBJECTID":36,"name":" ","source":" Captain Segulls Fishing Charts 2007"},"geometry":{"x":-80.41249999987325,"y":31.608316666700354}},{"attributes":{"OBJECTID":37,"name":" ","source":" Captain Segulls Fishing Charts 2007"},"geometry":{"x":-80.35249999940248,"y":31.687666666610035}},{"attributes":{"OBJECTID":38,"name":" ","source":" Captain Segulls Fishing Charts 2007"},"geometry":{"x":-80.35249999940248,"y":31.687666666610035}},{"attributes":{"OBJECTID":39,"name":" ","source":" Captain Segulls Fishing Charts 2007"},"geometry":{"x":-80.35249999940248,"y":31.687666666610035}},{"attributes":{"OBJECTID":40,"name":" ","source":" Captain Segulls Fishing Charts 2007"},"geometry":{"x":-80.21683333319355,"y":31.730000000048776}},{"attributes":{"OBJECTID":41,"name":" ","source":" Captain Segulls Fishing Charts 2007"},"geometry":{"x":-80.21683333319355,"y":31.730000000048776}},{"attributes":{"OBJECTID":42,"name":" ","source":" Captain Segulls Fishing Charts 2007"},"geometry":{"x":-80.21683333319355,"y":31.730000000048776}},{"attributes":{"OBJECTID":43,"name":" ","source":" Captain Segulls Fishing Charts 2007"},"geometry":{"x":-80.06583333328143,"y":31.883316667104825}},{"attributes":{"OBJECTID":44,"name":" ","source":" Captain Segulls Fishing Charts 2007"},"geometry":{"x":-80.06583333328143,"y":31.883316667104825}},{"attributes":{"OBJECTID":45,"name":" ","source":" Captain Segulls Fishing Charts 2007"},"geometry":{"x":-80.06583333328143,"y":31.883316667104825}},{"attributes":{"OBJECTID":46,"name":" ","source":" Captain Segulls Fishing Charts 2007"},"geometry":{"x":-80.30799999976452,"y":31.94583333335533}},{"attributes":{"OBJECTID":47,"name":" ","source":" Captain Segulls Fishing Charts 2007"},"geometry":{"x":-80.30799999976452,"y":31.94583333335533}},{"attributes":{"OBJECTID":48,"name":" ","source":" Captain Segulls Fishing Charts 2007"},"geometry":{"x":-80.30799999976452,"y":31.94583333335533}},{"attributes":{"OBJECTID":49,"name":"Hilton Head Reef","source":"Coastal Guide. 2007; NCDMF. 2007b"},"geometry":{"x":-80.72500000011671,"y":31.975000000424153}},{"attributes":{"OBJECTID":50,"name":"Hilton Head Reef","source":"Coastal Guide. 2007; NCDMF. 2007b"},"geometry":{"x":-80.72500000011671,"y":31.975000000424153}},{"attributes":{"OBJECTID":51,"name":"Hilton Head Reef","source":"Coastal Guide. 2007; NCDMF. 2007b"},"geometry":{"x":-80.72500000011671,"y":31.975000000424153}},{"attributes":{"OBJECTID":52,"name":" ","source":" Captain Segulls Fishing Charts 2007"},"geometry":{"x":-79.47533333340206,"y":31.98000000016374}},{"attributes":{"OBJECTID":53,"name":" ","source":" Captain Segulls Fishing Charts 2007"},"geometry":{"x":-79.47533333340206,"y":31.98000000016374}},{"attributes":{"OBJECTID":54,"name":" ","source":" Captain Segulls Fishing Charts 2007"},"geometry":{"x":-79.47533333340206,"y":31.98000000016374}},{"attributes":{"OBJECTID":55,"name":"Tybee Trough","source":" Captain Segulls Fishing Charts 2007"},"geometry":{"x":-80.35666666686292,"y":31.991666667043923}},{"attributes":{"OBJECTID":56,"name":"Tybee Trough","source":" Captain Segulls Fishing Charts 2007"},"geometry":{"x":-80.35666666686292,"y":31.991666667043923}},{"attributes":{"OBJECTID":57,"name":"Tybee Trough","source":" Captain Segulls Fishing Charts 2007"},"geometry":{"x":-80.35666666686292,"y":31.991666667043923}},{"attributes":{"OBJECTID":58,"name":"The Ridge","source":" Captain Segulls Fishing Charts 2007"},"geometry":{"x":-79.9541666663625,"y":32.0499666668512}},{"attributes":{"OBJECTID":59,"name":"The Ridge","source":" Captain Segulls Fishing Charts 2007"},"geometry":{"x":-79.9541666663625,"y":32.0499666668512}},{"attributes":{"OBJECTID":60,"name":"The Ridge","source":" Captain Segulls Fishing Charts 2007"},"geometry":{"x":-79.9541666663625,"y":32.0499666668512}},{"attributes":{"OBJECTID":61,"name":"Edisto Banks","source":" Captain Segulls Fishing Charts 2007"},"geometry":{"x":-79.40736666695325,"y":32.057916666242434}},{"attributes":{"OBJECTID":62,"name":"Edisto Banks","source":" Captain Segulls Fishing Charts 2007"},"geometry":{"x":-79.40736666695325,"y":32.057916666242434}},{"attributes":{"OBJECTID":63,"name":"Edisto Banks","source":" Captain Segulls Fishing Charts 2007"},"geometry":{"x":-79.40736666695325,"y":32.057916666242434}},{"attributes":{"OBJECTID":64,"name":"Gaskins Banks","source":"Coastal Guide. 2007; NCDMF. 2007b"},"geometry":{"x":-80.6999999998457,"y":32.10000000002851}},{"attributes":{"OBJECTID":65,"name":"Gaskins Banks","source":"Coastal Guide. 2007; NCDMF. 2007b"},"geometry":{"x":-80.6999999998457,"y":32.10000000002851}},{"attributes":{"OBJECTID":66,"name":"Gaskins Banks","source":"Coastal Guide. 2007; NCDMF. 2007b"},"geometry":{"x":-80.6999999998457,"y":32.10000000002851}},{"attributes":{"OBJECTID":67,"name":"South Channel","source":"Coastal Guide. 2007; NCDMF. 2007b"},"geometry":{"x":-80.61669999969371,"y":32.10000000002851}},{"attributes":{"OBJECTID":68,"name":"South Channel","source":"Coastal Guide. 2007; NCDMF. 2007b"},"geometry":{"x":-80.61669999969371,"y":32.10000000002851}},{"attributes":{"OBJECTID":69,"name":"South Channel","source":"Coastal Guide. 2007; NCDMF. 2007b"},"geometry":{"x":-80.61669999969371,"y":32.10000000002851}},{"attributes":{"OBJECTID":70,"name":"Southeast Channel","source":"Coastal Guide. 2007; NCDMF. 2007b"},"geometry":{"x":-80.5500000000163,"y":32.11670000010812}},{"attributes":{"OBJECTID":71,"name":"Southeast Channel","source":"Coastal Guide. 2007; NCDMF. 2007b"},"geometry":{"x":-80.5500000000163,"y":32.11670000010812}},{"attributes":{"OBJECTID":72,"name":"Southeast Channel","source":"Coastal Guide. 2007; NCDMF. 2007b"},"geometry":{"x":-80.5500000000163,"y":32.11670000010812}},{"attributes":{"OBJECTID":73,"name":" ","source":" Captain Segulls Fishing Charts 2007"},"geometry":{"x":-79.28941666640587,"y":32.14430000007439}},{"attributes":{"OBJECTID":74,"name":" ","source":" Captain Segulls Fishing Charts 2007"},"geometry":{"x":-79.28941666640587,"y":32.14430000007439}},{"attributes":{"OBJECTID":75,"name":" ","source":" Captain Segulls Fishing Charts 2007"},"geometry":{"x":-79.28941666640587,"y":32.14430000007439}},{"attributes":{"OBJECTID":76,"name":"Royal Terrace","source":" Captain Segulls Fishing Charts 2007"},"geometry":{"x":-79.17083333292193,"y":32.19998333372692}},{"attributes":{"OBJECTID":77,"name":"Royal Terrace","source":" Captain Segulls Fishing Charts 2007"},"geometry":{"x":-79.17083333292193,"y":32.19998333372692}},{"attributes":{"OBJECTID":78,"name":"Royal Terrace","source":" Captain Segulls Fishing Charts 2007"},"geometry":{"x":-79.17083333292193,"y":32.19998333372692}},{"attributes":{"OBJECTID":79,"name":"Hunting Island Reef","source":"Coastal Guide. 2007; NCDMF. 2007b"},"geometry":{"x":-80.32829999919764,"y":32.21329999996885}},{"attributes":{"OBJECTID":80,"name":"Hunting Island Reef","source":"Coastal Guide. 2007; NCDMF. 2007b"},"geometry":{"x":-80.32829999919764,"y":32.21329999996885}},{"attributes":{"OBJECTID":81,"name":"Hunting Island Reef","source":"Coastal Guide. 2007; NCDMF. 2007b"},"geometry":{"x":-80.32829999919764,"y":32.21329999996885}},{"attributes":{"OBJECTID":82,"name":" ","source":" Captain Segulls Fishing Charts 2007"},"geometry":{"x":-79.1601666662714,"y":32.24648333351289}},{"attributes":{"OBJECTID":83,"name":" ","source":" Captain Segulls Fishing Charts 2007"},"geometry":{"x":-79.1601666662714,"y":32.24648333351289}},{"attributes":{"OBJECTID":84,"name":" ","source":" Captain Segulls Fishing Charts 2007"},"geometry":{"x":-79.1601666662714,"y":32.24648333351289}},{"attributes":{"OBJECTID":85,"name":"Fripp Island Reef","source":"Coastal Guide. 2007; NCDMF. 2007b"},"geometry":{"x":-80.40000000018689,"y":32.31669999960924}},{"attributes":{"OBJECTID":86,"name":"Fripp Island Reef","source":"Coastal Guide. 2007; NCDMF. 2007b"},"geometry":{"x":-80.40000000018689,"y":32.31669999960924}},{"attributes":{"OBJECTID":87,"name":"Fripp Island Reef","source":"Coastal Guide. 2007; NCDMF. 2007b"},"geometry":{"x":-80.40000000018689,"y":32.31669999960924}},{"attributes":{"OBJECTID":88,"name":"Shell Break","source":" Captain Segulls Fishing Charts 2007"},"geometry":{"x":-79.04888333384038,"y":32.3466500005283}},{"attributes":{"OBJECTID":89,"name":"Shell Break","source":" Captain Segulls Fishing Charts 2007"},"geometry":{"x":-79.04888333384038,"y":32.3466500005283}},{"attributes":{"OBJECTID":90,"name":"Shell Break","source":" Captain Segulls Fishing Charts 2007"},"geometry":{"x":-79.04888333384038,"y":32.3466500005283}},{"attributes":{"OBJECTID":91,"name":" ","source":" Captain Segulls Fishing Charts 2007"},"geometry":{"x":-79.57050000030385,"y":32.36866666704831}},{"attributes":{"OBJECTID":92,"name":" ","source":" Captain Segulls Fishing Charts 2007"},"geometry":{"x":-79.57050000030385,"y":32.36866666704831}},{"attributes":{"OBJECTID":93,"name":" ","source":" Captain Segulls Fishing Charts 2007"},"geometry":{"x":-79.57050000030385,"y":32.36866666704831}},{"attributes":{"OBJECTID":94,"name":" ","source":" Captain Segulls Fishing Charts 2007"},"geometry":{"x":-78.89683333271853,"y":32.4706666672818}},{"attributes":{"OBJECTID":95,"name":" ","source":" Captain Segulls Fishing Charts 2007"},"geometry":{"x":-78.89683333271853,"y":32.4706666672818}},{"attributes":{"OBJECTID":96,"name":" ","source":" Captain Segulls Fishing Charts 2007"},"geometry":{"x":-78.89683333271853,"y":32.4706666672818}},{"attributes":{"OBJECTID":97,"name":" ","source":" Captain Segulls Fishing Charts 2007"},"geometry":{"x":-79.3335000004656,"y":32.475166666435996}},{"attributes":{"OBJECTID":98,"name":" ","source":" Captain Segulls Fishing Charts 2007"},"geometry":{"x":-79.3335000004656,"y":32.475166666435996}},{"attributes":{"OBJECTID":99,"name":" ","source":" Captain Segulls Fishing Charts 2007"},"geometry":{"x":-79.3335000004656,"y":32.475166666435996}},{"attributes":{"OBJECTID":100,"name":"Kiawab Reef (4KI)","source":"Coastal Guide. 2007; NCDMF. 2007b"},"geometry":{"x":-79.96669999983409,"y":32.4800000005253}},{"attributes":{"OBJECTID":101,"name":"Kiawab Reef (4KI)","source":"Coastal Guide. 2007; NCDMF. 2007b"},"geometry":{"x":-79.96669999983409,"y":32.4800000005253}},{"attributes":{"OBJECTID":102,"name":"Kiawab Reef (4KI)","source":"Coastal Guide. 2007; NCDMF. 2007b"},"geometry":{"x":-79.96669999983409,"y":32.4800000005253}},{"attributes":{"OBJECTID":103,"name":"S.W. Banks","source":" Captain Segulls Fishing Charts 2007"},"geometry":{"x":-78.83916666667241,"y":32.49163333381575}},{"attributes":{"OBJECTID":104,"name":"S.W. Banks","source":" Captain Segulls Fishing Charts 2007"},"geometry":{"x":-78.83916666667241,"y":32.49163333381575}},{"attributes":{"OBJECTID":105,"name":"S.W. Banks","source":" Captain Segulls Fishing Charts 2007"},"geometry":{"x":-78.83916666667241,"y":32.49163333381575}},{"attributes":{"OBJECTID":106,"name":" ","source":" Captain Segulls Fishing Charts 2007"},"geometry":{"x":-78.88683333278979,"y":32.52484999976056}},{"attributes":{"OBJECTID":107,"name":" ","source":" Captain Segulls Fishing Charts 2007"},"geometry":{"x":-78.88683333278979,"y":32.52484999976056}},{"attributes":{"OBJECTID":108,"name":" ","source":" Captain Segulls Fishing Charts 2007"},"geometry":{"x":-78.88683333278979,"y":32.52484999976056}},{"attributes":{"OBJECTID":109,"name":"Bulls Scarp","source":" Captain Segulls Fishing Charts 2007"},"geometry":{"x":-78.79483333326573,"y":32.524983333961124}},{"attributes":{"OBJECTID":110,"name":"Bulls Scarp","source":" Captain Segulls Fishing Charts 2007"},"geometry":{"x":-78.79483333326573,"y":32.524983333961124}},{"attributes":{"OBJECTID":111,"name":"Bulls Scarp","source":" Captain Segulls Fishing Charts 2007"},"geometry":{"x":-78.79483333326573,"y":32.524983333961124}},{"attributes":{"OBJECTID":112,"name":"Middle Ground","source":"Coastal Guide. 2007; NCDMF. 2007b"},"geometry":{"x":-80.12329999931102,"y":32.53330000074348}},{"attributes":{"OBJECTID":113,"name":"Middle Ground","source":"Coastal Guide. 2007; NCDMF. 2007b"},"geometry":{"x":-80.12329999931102,"y":32.53330000074348}},{"attributes":{"OBJECTID":114,"name":"Middle Ground","source":"Coastal Guide. 2007; NCDMF. 2007b"},"geometry":{"x":-80.12329999931102,"y":32.53330000074348}},{"attributes":{"OBJECTID":115,"name":"Deveaux Bank","source":"Coastal Guide. 2007; NCDMF. 2007b"},"geometry":{"x":-80.1667000002055,"y":32.54170000033729}},{"attributes":{"OBJECTID":116,"name":"Deveaux Bank","source":"Coastal Guide. 2007; NCDMF. 2007b"},"geometry":{"x":-80.1667000002055,"y":32.54170000033729}},{"attributes":{"OBJECTID":117,"name":"Deveaux Bank","source":"Coastal Guide. 2007; NCDMF. 2007b"},"geometry":{"x":-80.1667000002055,"y":32.54170000033729}},{"attributes":{"OBJECTID":118,"name":"Georgetown Hole","source":" Captain Segulls Fishing Charts 2007"},"geometry":{"x":-78.59166666641491,"y":32.54333333381043}},{"attributes":{"OBJECTID":119,"name":"Georgetown Hole","source":" Captain Segulls Fishing Charts 2007"},"geometry":{"x":-78.59166666641491,"y":32.54333333381043}},{"attributes":{"OBJECTID":120,"name":"Georgetown Hole","source":" Captain Segulls Fishing Charts 2007"},"geometry":{"x":-78.59166666641491,"y":32.54333333381043}},{"attributes":{"OBJECTID":121,"name":"Garden","source":" Captain Segulls Fishing Charts 2007"},"geometry":{"x":-79.35891666721317,"y":32.55465000045823}},{"attributes":{"OBJECTID":122,"name":"Garden","source":" Captain Segulls Fishing Charts 2007"},"geometry":{"x":-79.35891666721317,"y":32.55465000045823}},{"attributes":{"OBJECTID":123,"name":"Garden","source":" Captain Segulls Fishing Charts 2007"},"geometry":{"x":-79.35891666721317,"y":32.55465000045823}},{"attributes":{"OBJECTID":124,"name":" ","source":" Captain Segulls Fishing Charts 2007"},"geometry":{"x":-79.15825000011995,"y":32.61663333338124}},{"attributes":{"OBJECTID":125,"name":" ","source":" Captain Segulls Fishing Charts 2007"},"geometry":{"x":-79.15825000011995,"y":32.61663333338124}},{"attributes":{"OBJECTID":126,"name":" ","source":" Captain Segulls Fishing Charts 2007"},"geometry":{"x":-79.15825000011995,"y":32.61663333338124}},{"attributes":{"OBJECTID":127,"name":"Little Banks","source":"Coastal Guide. 2007; NCDMF. 2007b"},"geometry":{"x":-79.66670000017528,"y":32.70829999993917}},{"attributes":{"OBJECTID":128,"name":"Little Banks","source":"Coastal Guide. 2007; NCDMF. 2007b"},"geometry":{"x":-79.66670000017528,"y":32.70829999993917}},{"attributes":{"OBJECTID":129,"name":"Little Banks","source":"Coastal Guide. 2007; NCDMF. 2007b"},"geometry":{"x":-79.66670000017528,"y":32.70829999993917}},{"attributes":{"OBJECTID":130,"name":"Big Banks","source":"Coastal Guide. 2007; NCDMF. 2007b"},"geometry":{"x":-79.61670000053158,"y":32.73330000033761}},{"attributes":{"OBJECTID":131,"name":"Big Banks","source":"Coastal Guide. 2007; NCDMF. 2007b"},"geometry":{"x":-79.61670000053158,"y":32.73330000033761}},{"attributes":{"OBJECTID":132,"name":"Big Banks","source":"Coastal Guide. 2007; NCDMF. 2007b"},"geometry":{"x":-79.61670000053158,"y":32.73330000033761}},{"attributes":{"OBJECTID":133,"name":"Capers Reef (r-8)","source":"Coastal Guide. 2007; NCDMF. 2007b"},"geometry":{"x":-79.56669999998958,"y":32.73999999966972}},{"attributes":{"OBJECTID":134,"name":"Capers Reef (r-8)","source":"Coastal Guide. 2007; NCDMF. 2007b"},"geometry":{"x":-79.56669999998958,"y":32.73999999966972}},{"attributes":{"OBJECTID":135,"name":"Capers Reef (r-8)","source":"Coastal Guide. 2007; NCDMF. 2007b"},"geometry":{"x":-79.56669999998958,"y":32.73999999966972}},{"attributes":{"OBJECTID":136,"name":" ","source":" Captain Segulls Fishing Charts 2007"},"geometry":{"x":-79.22533333338697,"y":32.76668333355541}},{"attributes":{"OBJECTID":137,"name":" ","source":" Captain Segulls Fishing Charts 2007"},"geometry":{"x":-79.22533333338697,"y":32.76668333355541}},{"attributes":{"OBJECTID":138,"name":" ","source":" Captain Segulls Fishing Charts 2007"},"geometry":{"x":-79.22533333338697,"y":32.76668333355541}},{"attributes":{"OBJECTID":139,"name":"Winyah Scarp","source":" Captain Segulls Fishing Charts 2007"},"geometry":{"x":-78.40516666671087,"y":32.77166666696852}},{"attributes":{"OBJECTID":140,"name":"Winyah Scarp","source":" Captain Segulls Fishing Charts 2007"},"geometry":{"x":-78.40516666671087,"y":32.77166666696852}},{"attributes":{"OBJECTID":141,"name":"Winyah Scarp","source":" Captain Segulls Fishing Charts 2007"},"geometry":{"x":-78.40516666671087,"y":32.77166666696852}},{"attributes":{"OBJECTID":142,"name":" ","source":" Captain Segulls Fishing Charts 2007"},"geometry":{"x":-78.6166666657876,"y":32.84998333323464}},{"attributes":{"OBJECTID":143,"name":" ","source":" Captain Segulls Fishing Charts 2007"},"geometry":{"x":-78.6166666657876,"y":32.84998333323464}},{"attributes":{"OBJECTID":144,"name":" ","source":" Captain Segulls Fishing Charts 2007"},"geometry":{"x":-78.6166666657876,"y":32.84998333323464}},{"attributes":{"OBJECTID":145,"name":"Bull Breakers","source":"Coastal Guide. 2007; NCDMF. 2007b"},"geometry":{"x":-79.55830000019317,"y":32.85000000009846}},{"attributes":{"OBJECTID":146,"name":"Bull Breakers","source":"Coastal Guide. 2007; NCDMF. 2007b"},"geometry":{"x":-79.55830000019317,"y":32.85000000009846}},{"attributes":{"OBJECTID":147,"name":"Bull Breakers","source":"Coastal Guide. 2007; NCDMF. 2007b"},"geometry":{"x":-79.55830000019317,"y":32.85000000009846}},{"attributes":{"OBJECTID":148,"name":" ","source":" Captain Segulls Fishing Charts 2007"},"geometry":{"x":-79.28335000013577,"y":32.93300000018594}},{"attributes":{"OBJECTID":149,"name":" ","source":" Captain Segulls Fishing Charts 2007"},"geometry":{"x":-79.28335000013577,"y":32.93300000018594}},{"attributes":{"OBJECTID":150,"name":" ","source":" Captain Segulls Fishing Charts 2007"},"geometry":{"x":-79.28335000013577,"y":32.93300000018594}},{"attributes":{"OBJECTID":151,"name":"Cape Romain Shoal","source":"Coastal Guide. 2007; NCDMF. 2007b"},"geometry":{"x":-79.30670000004574,"y":32.978299999843344}},{"attributes":{"OBJECTID":152,"name":"Cape Romain Shoal","source":"Coastal Guide. 2007; NCDMF. 2007b"},"geometry":{"x":-79.30670000004574,"y":32.978299999843344}},{"attributes":{"OBJECTID":153,"name":"Cape Romain Shoal","source":"Coastal Guide. 2007; NCDMF. 2007b"},"geometry":{"x":-79.30670000004574,"y":32.978299999843344}},{"attributes":{"OBJECTID":154,"name":"Hector Wreck","source":"Coastal Guide. 2007; NCDMF. 2007b"},"geometry":{"x":-79.08329999953565,"y":33.000000000045986}},{"attributes":{"OBJECTID":155,"name":"Hector Wreck","source":"Coastal Guide. 2007; NCDMF. 2007b"},"geometry":{"x":-79.08329999953565,"y":33.000000000045986}},{"attributes":{"OBJECTID":156,"name":"Hector Wreck","source":"Coastal Guide. 2007; NCDMF. 2007b"},"geometry":{"x":-79.08329999953565,"y":33.000000000045986}},{"attributes":{"OBJECTID":157,"name":"City of Richmond Wreck","source":"Coastal Guide. 2007; NCDMF. 2007b"},"geometry":{"x":-79.08329999953565,"y":33.03669999967748}},{"attributes":{"OBJECTID":158,"name":"City of Richmond Wreck","source":"Coastal Guide. 2007; NCDMF. 2007b"},"geometry":{"x":-79.08329999953565,"y":33.03669999967748}},{"attributes":{"OBJECTID":159,"name":"City of Richmond Wreck","source":"Coastal Guide. 2007; NCDMF. 2007b"},"geometry":{"x":-79.08329999953565,"y":33.03669999967748}},{"attributes":{"OBJECTID":160,"name":" ","source":" Captain Segulls Fishing Charts 2007"},"geometry":{"x":-77.9166666662843,"y":33.06333333324047}},{"attributes":{"OBJECTID":161,"name":" ","source":" Captain Segulls Fishing Charts 2007"},"geometry":{"x":-77.9166666662843,"y":33.06333333324047}},{"attributes":{"OBJECTID":162,"name":" ","source":" Captain Segulls Fishing Charts 2007"},"geometry":{"x":-77.9166666662843,"y":33.06333333324047}},{"attributes":{"OBJECTID":163,"name":" ","source":" Captain Segulls Fishing Charts 2007"},"geometry":{"x":-77.67466666693083,"y":33.13733333363658}},{"attributes":{"OBJECTID":164,"name":" ","source":" Captain Segulls Fishing Charts 2007"},"geometry":{"x":-77.67466666693083,"y":33.13733333363658}},{"attributes":{"OBJECTID":165,"name":" ","source":" Captain Segulls Fishing Charts 2007"},"geometry":{"x":-77.67466666693083,"y":33.13733333363658}},{"attributes":{"OBJECTID":166,"name":"East Bank","source":"Coastal Guide. 2007; NCDMF. 2007b"},"geometry":{"x":-79.14170000077239,"y":33.15829999987978}},{"attributes":{"OBJECTID":167,"name":"East Bank","source":"Coastal Guide. 2007; NCDMF. 2007b"},"geometry":{"x":-79.14170000077239,"y":33.15829999987978}},{"attributes":{"OBJECTID":168,"name":"East Bank","source":"Coastal Guide. 2007; NCDMF. 2007b"},"geometry":{"x":-79.14170000077239,"y":33.15829999987978}},{"attributes":{"OBJECTID":169,"name":"Black Jack","source":" Captain Segulls Fishing Charts 2007"},"geometry":{"x":-77.4969999999432,"y":33.185666666540214}},{"attributes":{"OBJECTID":170,"name":"Black Jack","source":" Captain Segulls Fishing Charts 2007"},"geometry":{"x":-77.4969999999432,"y":33.185666666540214}},{"attributes":{"OBJECTID":171,"name":"Black Jack","source":" Captain Segulls Fishing Charts 2007"},"geometry":{"x":-77.4969999999432,"y":33.185666666540214}},{"attributes":{"OBJECTID":172,"name":"Steeples","source":" Captain Segulls Fishing Charts 2007"},"geometry":{"x":-77.32636666642146,"y":33.219266666878575}},{"attributes":{"OBJECTID":173,"name":"Steeples","source":" Captain Segulls Fishing Charts 2007"},"geometry":{"x":-77.32636666642146,"y":33.219266666878575}},{"attributes":{"OBJECTID":174,"name":"Steeples","source":" Captain Segulls Fishing Charts 2007"},"geometry":{"x":-77.32636666642146,"y":33.219266666878575}},{"attributes":{"OBJECTID":175,"name":"Steeples","source":" Captain Segulls Fishing Charts 2007"},"geometry":{"x":-77.31250000040457,"y":33.23499999997698}},{"attributes":{"OBJECTID":176,"name":"Steeples","source":" Captain Segulls Fishing Charts 2007"},"geometry":{"x":-77.31250000040457,"y":33.23499999997698}},{"attributes":{"OBJECTID":177,"name":"Steeples","source":" Captain Segulls Fishing Charts 2007"},"geometry":{"x":-77.31250000040457,"y":33.23499999997698}},{"attributes":{"OBJECTID":178,"name":"Twin City Wrecks","source":" Captain Segulls Fishing Charts 2007"},"geometry":{"x":-78.0305333333852,"y":33.2694333332366}},{"attributes":{"OBJECTID":179,"name":"Twin City Wrecks","source":" Captain Segulls Fishing Charts 2007"},"geometry":{"x":-78.0305333333852,"y":33.2694333332366}},{"attributes":{"OBJECTID":180,"name":"Twin City Wrecks","source":" Captain Segulls Fishing Charts 2007"},"geometry":{"x":-78.0305333333852,"y":33.2694333332366}},{"attributes":{"OBJECTID":181,"name":"Cape Fear Terrace","source":" Captain Segulls Fishing Charts 2007"},"geometry":{"x":-77.32030000015138,"y":33.290316666551554}},{"attributes":{"OBJECTID":182,"name":"Cape Fear Terrace","source":" Captain Segulls Fishing Charts 2007"},"geometry":{"x":-77.32030000015138,"y":33.290316666551554}},{"attributes":{"OBJECTID":183,"name":"Cape Fear Terrace","source":" Captain Segulls Fishing Charts 2007"},"geometry":{"x":-77.32030000015138,"y":33.290316666551554}},{"attributes":{"OBJECTID":184,"name":"Cape Fear Terrace","source":" Captain Segulls Fishing Charts 2007"},"geometry":{"x":-77.36063333322723,"y":33.30288333345481}},{"attributes":{"OBJECTID":185,"name":"Cape Fear Terrace","source":" Captain Segulls Fishing Charts 2007"},"geometry":{"x":-77.36063333322723,"y":33.30288333345481}},{"attributes":{"OBJECTID":186,"name":"Cape Fear Terrace","source":" Captain Segulls Fishing Charts 2007"},"geometry":{"x":-77.36063333322723,"y":33.30288333345481}},{"attributes":{"OBJECTID":187,"name":"Cape Fear Terrace","source":" Captain Segulls Fishing Charts 2007"},"geometry":{"x":-77.37218333305958,"y":33.323633333831864}},{"attributes":{"OBJECTID":188,"name":"Cape Fear Terrace","source":" Captain Segulls Fishing Charts 2007"},"geometry":{"x":-77.37218333305958,"y":33.323633333831864}},{"attributes":{"OBJECTID":189,"name":"Cape Fear Terrace","source":" Captain Segulls Fishing Charts 2007"},"geometry":{"x":-77.37218333305958,"y":33.323633333831864}},{"attributes":{"OBJECTID":190,"name":"32 Mile Rock","source":" Captain Segulls Fishing Charts 2007"},"geometry":{"x":-78.31520000023914,"y":33.358533333179224}},{"attributes":{"OBJECTID":191,"name":"32 Mile Rock","source":" Captain Segulls Fishing Charts 2007"},"geometry":{"x":-78.31520000023914,"y":33.358533333179224}},{"attributes":{"OBJECTID":192,"name":"32 Mile Rock","source":" Captain Segulls Fishing Charts 2007"},"geometry":{"x":-78.31520000023914,"y":33.358533333179224}},{"attributes":{"OBJECTID":193,"name":"Ten Mile Reef","source":"Coastal Guide. 2007; NCDMF. 2007b"},"geometry":{"x":-78.87665999933371,"y":33.435000000014156}},{"attributes":{"OBJECTID":194,"name":"Ten Mile Reef","source":"Coastal Guide. 2007; NCDMF. 2007b"},"geometry":{"x":-78.87665999933371,"y":33.435000000014156}},{"attributes":{"OBJECTID":195,"name":"Ten Mile Reef","source":"Coastal Guide. 2007; NCDMF. 2007b"},"geometry":{"x":-78.87665999933371,"y":33.435000000014156}},{"attributes":{"OBJECTID":196,"name":"Paridise Reef","source":"Coastal Guide. 2007; NCDMF. 2007b"},"geometry":{"x":-78.96166000007547,"y":33.51165999969437}},{"attributes":{"OBJECTID":197,"name":"Paridise Reef","source":"Coastal Guide. 2007; NCDMF. 2007b"},"geometry":{"x":-78.96166000007547,"y":33.51165999969437}},{"attributes":{"OBJECTID":198,"name":"Paridise Reef","source":"Coastal Guide. 2007; NCDMF. 2007b"},"geometry":{"x":-78.96166000007547,"y":33.51165999969437}},{"attributes":{"OBJECTID":199,"name":" ","source":" Captain Segulls Fishing Charts 2007"},"geometry":{"x":-77.14000000006178,"y":33.54999999926291}},{"attributes":{"OBJECTID":200,"name":" ","source":" Captain Segulls Fishing Charts 2007"},"geometry":{"x":-77.14000000006178,"y":33.54999999926291}},{"attributes":{"OBJECTID":201,"name":" ","source":" Captain Segulls Fishing Charts 2007"},"geometry":{"x":-77.14000000006178,"y":33.54999999926291}},{"attributes":{"OBJECTID":202,"name":" ","source":" Captain Segulls Fishing Charts 2007"},"geometry":{"x":-77.3208333335288,"y":33.59591666664321}},{"attributes":{"OBJECTID":203,"name":" ","source":" Captain Segulls Fishing Charts 2007"},"geometry":{"x":-77.3208333335288,"y":33.59591666664321}},{"attributes":{"OBJECTID":204,"name":" ","source":" Captain Segulls Fishing Charts 2007"},"geometry":{"x":-77.3208333335288,"y":33.59591666664321}},{"attributes":{"OBJECTID":205,"name":" ","source":" Captain Segulls Fishing Charts 2007"},"geometry":{"x":-77.06249999949115,"y":33.654166666687665}},{"attributes":{"OBJECTID":206,"name":" ","source":" Captain Segulls Fishing Charts 2007"},"geometry":{"x":-77.06249999949115,"y":33.654166666687665}},{"attributes":{"OBJECTID":207,"name":" ","source":" Captain Segulls Fishing Charts 2007"},"geometry":{"x":-77.06249999949115,"y":33.654166666687665}},{"attributes":{"OBJECTID":208,"name":" ","source":" Captain Segulls Fishing Charts 2007"},"geometry":{"x":-77.49999999929301,"y":33.65866666696056}},{"attributes":{"OBJECTID":209,"name":" ","source":" Captain Segulls Fishing Charts 2007"},"geometry":{"x":-77.49999999929301,"y":33.65866666696056}},{"attributes":{"OBJECTID":210,"name":" ","source":" Captain Segulls Fishing Charts 2007"},"geometry":{"x":-77.49999999929301,"y":33.65866666696056}},{"attributes":{"OBJECTID":211,"name":"Frying Pan ledges East","source":"Coastal Guide. 2007; NCDMF. 2007b"},"geometry":{"x":-77.88276538832204,"y":33.68352033305002}},{"attributes":{"OBJECTID":212,"name":"Frying Pan ledges East","source":"Coastal Guide. 2007; NCDMF. 2007b"},"geometry":{"x":-77.88276538832204,"y":33.68352033305002}},{"attributes":{"OBJECTID":213,"name":"Frying Pan ledges East","source":"Coastal Guide. 2007; NCDMF. 2007b"},"geometry":{"x":-77.88276538832204,"y":33.68352033305002}},{"attributes":{"OBJECTID":214,"name":" ","source":" Captain Segulls Fishing Charts 2007"},"geometry":{"x":-77.28583333332905,"y":33.73333333336353}},{"attributes":{"OBJECTID":215,"name":" ","source":" Captain Segulls Fishing Charts 2007"},"geometry":{"x":-77.28583333332905,"y":33.73333333336353}},{"attributes":{"OBJECTID":216,"name":" ","source":" Captain Segulls Fishing Charts 2007"},"geometry":{"x":-77.28583333332905,"y":33.73333333336353}},{"attributes":{"OBJECTID":217,"name":" ","source":" Captain Segulls Fishing Charts 2007"},"geometry":{"x":-76.54775000026224,"y":33.820583332855506}},{"attributes":{"OBJECTID":218,"name":" ","source":" Captain Segulls Fishing Charts 2007"},"geometry":{"x":-76.54775000026224,"y":33.820583332855506}},{"attributes":{"OBJECTID":219,"name":" ","source":" Captain Segulls Fishing Charts 2007"},"geometry":{"x":-76.54775000026224,"y":33.820583332855506}},{"attributes":{"OBJECTID":220,"name":" ","source":" Captain Segulls Fishing Charts 2007"},"geometry":{"x":-76.52553333288103,"y":33.835983333861954}},{"attributes":{"OBJECTID":221,"name":" ","source":" Captain Segulls Fishing Charts 2007"},"geometry":{"x":-76.52553333288103,"y":33.835983333861954}},{"attributes":{"OBJECTID":222,"name":" ","source":" Captain Segulls Fishing Charts 2007"},"geometry":{"x":-76.52553333288103,"y":33.835983333861954}},{"attributes":{"OBJECTID":223,"name":" ","source":" Captain Segulls Fishing Charts 2007"},"geometry":{"x":-77.30850000007376,"y":33.85016666674878}},{"attributes":{"OBJECTID":224,"name":" ","source":" Captain Segulls Fishing Charts 2007"},"geometry":{"x":-77.30850000007376,"y":33.85016666674878}},{"attributes":{"OBJECTID":225,"name":" ","source":" Captain Segulls Fishing Charts 2007"},"geometry":{"x":-77.30850000007376,"y":33.85016666674878}},{"attributes":{"OBJECTID":226,"name":" ","source":" Captain Segulls Fishing Charts 2007"},"geometry":{"x":-76.54208333312693,"y":33.86885000035961}},{"attributes":{"OBJECTID":227,"name":" ","source":" Captain Segulls Fishing Charts 2007"},"geometry":{"x":-76.54208333312693,"y":33.86885000035961}},{"attributes":{"OBJECTID":228,"name":" ","source":" Captain Segulls Fishing Charts 2007"},"geometry":{"x":-76.54208333312693,"y":33.86885000035961}},{"attributes":{"OBJECTID":229,"name":"Swansboro Hole","source":" Captain Segulls Fishing Charts 2007"},"geometry":{"x":-76.45416666704932,"y":33.90250000002164}},{"attributes":{"OBJECTID":230,"name":"Swansboro Hole","source":" Captain Segulls Fishing Charts 2007"},"geometry":{"x":-76.45416666704932,"y":33.90250000002164}},{"attributes":{"OBJECTID":231,"name":"Swansboro Hole","source":" Captain Segulls Fishing Charts 2007"},"geometry":{"x":-76.45416666704932,"y":33.90250000002164}},{"attributes":{"OBJECTID":232,"name":" ","source":" Captain Segulls Fishing Charts 2007"},"geometry":{"x":-76.38329999991149,"y":34.004166666743735}},{"attributes":{"OBJECTID":233,"name":" ","source":" Captain Segulls Fishing Charts 2007"},"geometry":{"x":-76.38329999991149,"y":34.004166666743735}},{"attributes":{"OBJECTID":234,"name":" ","source":" Captain Segulls Fishing Charts 2007"},"geometry":{"x":-76.38329999991149,"y":34.004166666743735}},{"attributes":{"OBJECTID":235,"name":" ","source":" Captain Segulls Fishing Charts 2007"},"geometry":{"x":-77.35849999971745,"y":34.02500000062511}},{"attributes":{"OBJECTID":236,"name":" ","source":" Captain Segulls Fishing Charts 2007"},"geometry":{"x":-77.35849999971745,"y":34.02500000062511}},{"attributes":{"OBJECTID":237,"name":" ","source":" Captain Segulls Fishing Charts 2007"},"geometry":{"x":-77.35849999971745,"y":34.02500000062511}},{"attributes":{"OBJECTID":238,"name":" ","source":" Captain Segulls Fishing Charts 2007"},"geometry":{"x":-76.28333333351102,"y":34.03333333356482}},{"attributes":{"OBJECTID":239,"name":" ","source":" Captain Segulls Fishing Charts 2007"},"geometry":{"x":-76.28333333351102,"y":34.03333333356482}},{"attributes":{"OBJECTID":240,"name":" ","source":" Captain Segulls Fishing Charts 2007"},"geometry":{"x":-76.28333333351102,"y":34.03333333356482}},{"attributes":{"OBJECTID":241,"name":"Papoose","source":"Coastal Guide. 2007; NCDMF. 2007b"},"geometry":{"x":-76.61670000035032,"y":34.1166999998804}},{"attributes":{"OBJECTID":242,"name":"Papoose","source":"Coastal Guide. 2007; NCDMF. 2007b"},"geometry":{"x":-76.61670000035032,"y":34.1166999998804}},{"attributes":{"OBJECTID":243,"name":"Papoose","source":"Coastal Guide. 2007; NCDMF. 2007b"},"geometry":{"x":-76.61670000035032,"y":34.1166999998804}},{"attributes":{"OBJECTID":244,"name":"Marlin Grounds","source":"Coastal Guide. 2007; NCDMF. 2007b"},"geometry":{"x":-76.11670000032011,"y":34.1166999998804}},{"attributes":{"OBJECTID":245,"name":"Marlin Grounds","source":"Coastal Guide. 2007; NCDMF. 2007b"},"geometry":{"x":-76.11670000032011,"y":34.1166999998804}},{"attributes":{"OBJECTID":246,"name":"Marlin Grounds","source":"Coastal Guide. 2007; NCDMF. 2007b"},"geometry":{"x":-76.11670000032011,"y":34.1166999998804}},{"attributes":{"OBJECTID":247,"name":" ","source":" Captain Segulls Fishing Charts 2007"},"geometry":{"x":-76.3999999999452,"y":34.1291666663551}},{"attributes":{"OBJECTID":248,"name":" ","source":" Captain Segulls Fishing Charts 2007"},"geometry":{"x":-76.3999999999452,"y":34.1291666663551}},{"attributes":{"OBJECTID":249,"name":" ","source":" Captain Segulls Fishing Charts 2007"},"geometry":{"x":-76.3999999999452,"y":34.1291666663551}},{"attributes":{"OBJECTID":250,"name":" ","source":" Captain Segulls Fishing Charts 2007"},"geometry":{"x":-76.29998333331602,"y":34.150166666981264}},{"attributes":{"OBJECTID":251,"name":" ","source":" Captain Segulls Fishing Charts 2007"},"geometry":{"x":-76.29998333331602,"y":34.150166666981264}},{"attributes":{"OBJECTID":252,"name":" ","source":" Captain Segulls Fishing Charts 2007"},"geometry":{"x":-76.29998333331602,"y":34.150166666981264}},{"attributes":{"OBJECTID":253,"name":"Big Rock","source":" Captain Segulls Fishing Charts 2007"},"geometry":{"x":-76.16975000044063,"y":34.151566666854784}},{"attributes":{"OBJECTID":254,"name":"Big Rock","source":" Captain Segulls Fishing Charts 2007"},"geometry":{"x":-76.16975000044063,"y":34.151566666854784}},{"attributes":{"OBJECTID":255,"name":"Big Rock","source":" Captain Segulls Fishing Charts 2007"},"geometry":{"x":-76.16975000044063,"y":34.151566666854784}},{"attributes":{"OBJECTID":256,"name":"Black Rock","source":"Coastal Guide. 2007; NCDMF. 2007b"},"geometry":{"x":-76.11659999986266,"y":34.18329999988898}},{"attributes":{"OBJECTID":257,"name":"Black Rock","source":"Coastal Guide. 2007; NCDMF. 2007b"},"geometry":{"x":-76.11659999986266,"y":34.18329999988898}},{"attributes":{"OBJECTID":258,"name":"Black Rock","source":"Coastal Guide. 2007; NCDMF. 2007b"},"geometry":{"x":-76.11659999986266,"y":34.18329999988898}},{"attributes":{"OBJECTID":259,"name":"90' Ledge","source":" Captain Segulls Fishing Charts 2007"},"geometry":{"x":-76.25345000062569,"y":34.2093499999491}},{"attributes":{"OBJECTID":260,"name":"90' Ledge","source":" Captain Segulls Fishing Charts 2007"},"geometry":{"x":-76.25345000062569,"y":34.2093499999491}},{"attributes":{"OBJECTID":261,"name":"90' Ledge","source":" Captain Segulls Fishing Charts 2007"},"geometry":{"x":-76.25345000062569,"y":34.2093499999491}},{"attributes":{"OBJECTID":262,"name":"Snowy Hole","source":"Coastal Guide. 2007; NCDMF. 2007b"},"geometry":{"x":-76.03329999971066,"y":34.23000000009507}},{"attributes":{"OBJECTID":263,"name":"Snowy Hole","source":"Coastal Guide. 2007; NCDMF. 2007b"},"geometry":{"x":-76.03329999971066,"y":34.23000000009507}},{"attributes":{"OBJECTID":264,"name":"Snowy Hole","source":"Coastal Guide. 2007; NCDMF. 2007b"},"geometry":{"x":-76.03329999971066,"y":34.23000000009507}},{"attributes":{"OBJECTID":265,"name":" ","source":" Captain Segulls Fishing Charts 2007"},"geometry":{"x":-76.373333333768,"y":34.242000000142646}},{"attributes":{"OBJECTID":266,"name":" ","source":" Captain Segulls Fishing Charts 2007"},"geometry":{"x":-76.373333333768,"y":34.242000000142646}},{"attributes":{"OBJECTID":267,"name":" ","source":" Captain Segulls Fishing Charts 2007"},"geometry":{"x":-76.373333333768,"y":34.242000000142646}},{"attributes":{"OBJECTID":268,"name":"210 Rock","source":"Coastal Guide. 2007; NCDMF. 2007b"},"geometry":{"x":-76.6332999999266,"y":34.24999999988459}},{"attributes":{"OBJECTID":269,"name":"210 Rock","source":"Coastal Guide. 2007; NCDMF. 2007b"},"geometry":{"x":-76.6332999999266,"y":34.24999999988459}},{"attributes":{"OBJECTID":270,"name":"210 Rock","source":"Coastal Guide. 2007; NCDMF. 2007b"},"geometry":{"x":-76.6332999999266,"y":34.24999999988459}},{"attributes":{"OBJECTID":271,"name":" ","source":" Captain Segulls Fishing Charts 2007"},"geometry":{"x":-76.16700000043777,"y":34.27498333370158}},{"attributes":{"OBJECTID":272,"name":" ","source":" Captain Segulls Fishing Charts 2007"},"geometry":{"x":-76.16700000043777,"y":34.27498333370158}},{"attributes":{"OBJECTID":273,"name":" ","source":" Captain Segulls Fishing Charts 2007"},"geometry":{"x":-76.16700000043777,"y":34.27498333370158}},{"attributes":{"OBJECTID":274,"name":" ","source":" Captain Segulls Fishing Charts 2007"},"geometry":{"x":-76.24249999994466,"y":34.27750000016756}},{"attributes":{"OBJECTID":275,"name":" ","source":" Captain Segulls Fishing Charts 2007"},"geometry":{"x":-76.24249999994466,"y":34.27750000016756}},{"attributes":{"OBJECTID":276,"name":" ","source":" Captain Segulls Fishing Charts 2007"},"geometry":{"x":-76.24249999994466,"y":34.27750000016756}},{"attributes":{"OBJECTID":277,"name":"West Rock","source":"Coastal Guide. 2007; NCDMF. 2007b"},"geometry":{"x":-76.5833000002829,"y":34.299999999944674}},{"attributes":{"OBJECTID":278,"name":"West Rock","source":"Coastal Guide. 2007; NCDMF. 2007b"},"geometry":{"x":-76.5833000002829,"y":34.299999999944674}},{"attributes":{"OBJECTID":279,"name":"West Rock","source":"Coastal Guide. 2007; NCDMF. 2007b"},"geometry":{"x":-76.5833000002829,"y":34.299999999944674}},{"attributes":{"OBJECTID":280,"name":" ","source":" Captain Segulls Fishing Charts 2007"},"geometry":{"x":-76.97944999958442,"y":34.332500000185426}},{"attributes":{"OBJECTID":281,"name":" ","source":" Captain Segulls Fishing Charts 2007"},"geometry":{"x":-76.97944999958442,"y":34.332500000185426}},{"attributes":{"OBJECTID":282,"name":" ","source":" Captain Segulls Fishing Charts 2007"},"geometry":{"x":-76.97944999958442,"y":34.332500000185426}},{"attributes":{"OBJECTID":283,"name":" ","source":" Captain Segulls Fishing Charts 2007"},"geometry":{"x":-76.00000000010068,"y":34.33333333366464}},{"attributes":{"OBJECTID":284,"name":" ","source":" Captain Segulls Fishing Charts 2007"},"geometry":{"x":-76.00000000010068,"y":34.33333333366464}},{"attributes":{"OBJECTID":285,"name":" ","source":" Captain Segulls Fishing Charts 2007"},"geometry":{"x":-76.00000000010068,"y":34.33333333366464}},{"attributes":{"OBJECTID":286,"name":"10 Fathom  Ledge","source":"Coastal Guide. 2007; NCDMF. 2007b"},"geometry":{"x":-76.5666999998083,"y":34.383299999935616}},{"attributes":{"OBJECTID":287,"name":"10 Fathom  Ledge","source":"Coastal Guide. 2007; NCDMF. 2007b"},"geometry":{"x":-76.5666999998083,"y":34.383299999935616}},{"attributes":{"OBJECTID":288,"name":"10 Fathom  Ledge","source":"Coastal Guide. 2007; NCDMF. 2007b"},"geometry":{"x":-76.5666999998083,"y":34.383299999935616}},{"attributes":{"OBJECTID":289,"name":"Northwest Place","source":"Coastal Guide. 2007; NCDMF. 2007b"},"geometry":{"x":-76.59999999941829,"y":34.43330000046892}},{"attributes":{"OBJECTID":290,"name":"Northwest Place","source":"Coastal Guide. 2007; NCDMF. 2007b"},"geometry":{"x":-76.59999999941829,"y":34.43330000046892}},{"attributes":{"OBJECTID":291,"name":"Northwest Place","source":"Coastal Guide. 2007; NCDMF. 2007b"},"geometry":{"x":-76.59999999941829,"y":34.43330000046892}},{"attributes":{"OBJECTID":292,"name":" ","source":" Captain Segulls Fishing Charts 2007"},"geometry":{"x":-75.86000000020002,"y":34.43333333357601}},{"attributes":{"OBJECTID":293,"name":" ","source":" Captain Segulls Fishing Charts 2007"},"geometry":{"x":-75.86000000020002,"y":34.43333333357601}},{"attributes":{"OBJECTID":294,"name":" ","source":" Captain Segulls Fishing Charts 2007"},"geometry":{"x":-75.86000000020002,"y":34.43333333357601}},{"attributes":{"OBJECTID":295,"name":"Cape Lookout Shoals","source":"Coastal Guide. 2007; NCDMF. 2007b"},"geometry":{"x":-76.50000000013091,"y":34.51669999972924}},{"attributes":{"OBJECTID":296,"name":"Cape Lookout Shoals","source":"Coastal Guide. 2007; NCDMF. 2007b"},"geometry":{"x":-76.50000000013091,"y":34.51669999972924}},{"attributes":{"OBJECTID":297,"name":"Cape Lookout Shoals","source":"Coastal Guide. 2007; NCDMF. 2007b"},"geometry":{"x":-76.50000000013091,"y":34.51669999972924}},{"attributes":{"OBJECTID":298,"name":"Tamaulipas","source":" Captain Segulls Fishing Charts 2007"},"geometry":{"x":-75.01350000070764,"y":34.54656666639383}},{"attributes":{"OBJECTID":299,"name":"Tamaulipas","source":" Captain Segulls Fishing Charts 2007"},"geometry":{"x":-75.01350000070764,"y":34.54656666639383}},{"attributes":{"OBJECTID":300,"name":"Tamaulipas","source":" Captain Segulls Fishing Charts 2007"},"geometry":{"x":-75.01350000070764,"y":34.54656666639383}},{"attributes":{"OBJECTID":301,"name":" ","source":" Captain Segulls Fishing Charts 2007"},"geometry":{"x":-76.74996666725909,"y":34.61666666615783}},{"attributes":{"OBJECTID":302,"name":" ","source":" Captain Segulls Fishing Charts 2007"},"geometry":{"x":-76.74996666725909,"y":34.61666666615783}},{"attributes":{"OBJECTID":303,"name":" ","source":" Captain Segulls Fishing Charts 2007"},"geometry":{"x":-76.74996666725909,"y":34.61666666615783}},{"attributes":{"OBJECTID":304,"name":" ","source":" Captain Segulls Fishing Charts 2007"},"geometry":{"x":-75.74996666630034,"y":34.61666666615783}},{"attributes":{"OBJECTID":305,"name":" ","source":" Captain Segulls Fishing Charts 2007"},"geometry":{"x":-75.74996666630034,"y":34.61666666615783}},{"attributes":{"OBJECTID":306,"name":" ","source":" Captain Segulls Fishing Charts 2007"},"geometry":{"x":-75.74996666630034,"y":34.61666666615783}},{"attributes":{"OBJECTID":307,"name":"The Duck","source":" Captain Segulls Fishing Charts 2007"},"geometry":{"x":-76.13833333319685,"y":34.627500000264156}},{"attributes":{"OBJECTID":308,"name":"The Duck","source":" Captain Segulls Fishing Charts 2007"},"geometry":{"x":-76.13833333319685,"y":34.627500000264156}},{"attributes":{"OBJECTID":309,"name":"The Duck","source":" Captain Segulls Fishing Charts 2007"},"geometry":{"x":-76.13833333319685,"y":34.627500000264156}},{"attributes":{"OBJECTID":310,"name":" ","source":" Captain Segulls Fishing Charts 2007"},"geometry":{"x":-75.950000000457,"y":34.73833333330009}},{"attributes":{"OBJECTID":311,"name":" ","source":" Captain Segulls Fishing Charts 2007"},"geometry":{"x":-75.950000000457,"y":34.73833333330009}},{"attributes":{"OBJECTID":312,"name":" ","source":" Captain Segulls Fishing Charts 2007"},"geometry":{"x":-75.950000000457,"y":34.73833333330009}},{"attributes":{"OBJECTID":313,"name":" ","source":" Captain Segulls Fishing Charts 2007"},"geometry":{"x":-75.950000000457,"y":34.73833333330009}},{"attributes":{"OBJECTID":314,"name":" ","source":" Captain Segulls Fishing Charts 2007"},"geometry":{"x":-75.950000000457,"y":34.73833333330009}},{"attributes":{"OBJECTID":315,"name":" ","source":" Captain Segulls Fishing Charts 2007"},"geometry":{"x":-75.950000000457,"y":34.73833333330009}},{"attributes":{"OBJECTID":316,"name":" ","source":" Captain Segulls Fishing Charts 2007"},"geometry":{"x":-75.41250000046944,"y":34.82749999980185}},{"attributes":{"OBJECTID":317,"name":" ","source":" Captain Segulls Fishing Charts 2007"},"geometry":{"x":-75.41250000046944,"y":34.82749999980185}},{"attributes":{"OBJECTID":318,"name":" ","source":" Captain Segulls Fishing Charts 2007"},"geometry":{"x":-75.41250000046944,"y":34.82749999980185}},{"attributes":{"OBJECTID":319,"name":" ","source":" Captain Segulls Fishing Charts 2007"},"geometry":{"x":-75.41250000046944,"y":34.82749999980185}},{"attributes":{"OBJECTID":320,"name":" ","source":" Captain Segulls Fishing Charts 2007"},"geometry":{"x":-75.41250000046944,"y":34.82749999980185}},{"attributes":{"OBJECTID":321,"name":" ","source":" Captain Segulls Fishing Charts 2007"},"geometry":{"x":-75.41250000046944,"y":34.82749999980185}},{"attributes":{"OBJECTID":322,"name":"Rock Pile","source":" Captain Segulls Fishing Charts 2007"},"geometry":{"x":-75.50000000007047,"y":34.86333333305131}},{"attributes":{"OBJECTID":323,"name":" ","source":" Captain Segulls Fishing Charts 2007"},"geometry":{"x":-75.50000000007047,"y":34.86333333305131}},{"attributes":{"OBJECTID":324,"name":"Rock Pile","source":" Captain Segulls Fishing Charts 2007"},"geometry":{"x":-75.50000000007047,"y":34.86333333305131}},{"attributes":{"OBJECTID":325,"name":" ","source":" Captain Segulls Fishing Charts 2007"},"geometry":{"x":-75.50000000007047,"y":34.86333333305131}},{"attributes":{"OBJECTID":326,"name":"Rock Pile","source":" Captain Segulls Fishing Charts 2007"},"geometry":{"x":-75.50000000007047,"y":34.86333333305131}},{"attributes":{"OBJECTID":327,"name":" ","source":" Captain Segulls Fishing Charts 2007"},"geometry":{"x":-75.50000000007047,"y":34.86333333305131}},{"attributes":{"OBJECTID":328,"name":"Offshore Lump (Ridge)","source":"Coastal Guide. 2007; NCDMF. 2007b"},"geometry":{"x":-75.56670000064618,"y":34.86670000021677}},{"attributes":{"OBJECTID":329,"name":"Offshore Lump (Ridge)","source":"Coastal Guide. 2007; NCDMF. 2007b"},"geometry":{"x":-75.56670000064618,"y":34.86670000021677}},{"attributes":{"OBJECTID":330,"name":"Offshore Lump (Ridge)","source":"Coastal Guide. 2007; NCDMF. 2007b"},"geometry":{"x":-75.56670000064618,"y":34.86670000021677}},{"attributes":{"OBJECTID":331,"name":" ","source":" Captain Segulls Fishing Charts 2007"},"geometry":{"x":-75.39416666651815,"y":34.958333333664676}},{"attributes":{"OBJECTID":332,"name":" ","source":" Captain Segulls Fishing Charts 2007"},"geometry":{"x":-75.39416666651815,"y":34.958333333664676}},{"attributes":{"OBJECTID":333,"name":" ","source":" Captain Segulls Fishing Charts 2007"},"geometry":{"x":-75.39416666651815,"y":34.958333333664676}},{"attributes":{"OBJECTID":334,"name":" ","source":" Captain Segulls Fishing Charts 2007"},"geometry":{"x":-74.70833333260738,"y":35.08333333338094}},{"attributes":{"OBJECTID":335,"name":" ","source":" Captain Segulls Fishing Charts 2007"},"geometry":{"x":-74.70833333260738,"y":35.08333333338094}},{"attributes":{"OBJECTID":336,"name":" ","source":" Captain Segulls Fishing Charts 2007"},"geometry":{"x":-74.70833333260738,"y":35.08333333338094}},{"attributes":{"OBJECTID":337,"name":"Diamond Shoals","source":"Coastal Guide. 2007; NCDMF. 2007b"},"geometry":{"x":-75.41669999991848,"y":35.166700000172725}},{"attributes":{"OBJECTID":338,"name":"Diamond Shoals","source":"Various sources, reference metadata"},"geometry":{"x":-75.41669999991848,"y":35.166700000172725}},{"attributes":{"OBJECTID":339,"name":"Diamond Shoals","source":"Coastal Guide. 2007; NCDMF. 2007b"},"geometry":{"x":-75.41669999991848,"y":35.166700000172725}},{"attributes":{"OBJECTID":340,"name":"Diamond Shoals","source":"Various sources, reference metadata"},"geometry":{"x":-75.41669999991848,"y":35.166700000172725}},{"attributes":{"OBJECTID":341,"name":"Diamond Shoals","source":"Coastal Guide. 2007; NCDMF. 2007b"},"geometry":{"x":-75.41669999991848,"y":35.166700000172725}},{"attributes":{"OBJECTID":342,"name":"Diamond Shoals","source":"Various sources, reference metadata"},"geometry":{"x":-75.41669999991848,"y":35.166700000172725}},{"attributes":{"OBJECTID":343,"name":"Hatteras Shoals","source":"Coastal Guide. 2007; NCDMF. 2007b"},"geometry":{"x":-75.48330000003678,"y":35.20000000019553}},{"attributes":{"OBJECTID":344,"name":"Hatteras Shoals","source":"Coastal Guide. 2007; NCDMF. 2007b"},"geometry":{"x":-75.48330000003678,"y":35.20000000019553}},{"attributes":{"OBJECTID":345,"name":"Hatteras Shoals","source":"Coastal Guide. 2007; NCDMF. 2007b"},"geometry":{"x":-75.48330000003678,"y":35.20000000019553}},{"attributes":{"OBJECTID":346,"name":"Old Green Line","source":" Captain Segulls Fishing Charts 2007"},"geometry":{"x":-74.97461666707797,"y":35.27408333355128}},{"attributes":{"OBJECTID":347,"name":"Old Green Line","source":" Captain Segulls Fishing Charts 2007"},"geometry":{"x":-74.97461666707797,"y":35.27408333355128}},{"attributes":{"OBJECTID":348,"name":"Old Green Line","source":" Captain Segulls Fishing Charts 2007"},"geometry":{"x":-74.97461666707797,"y":35.27408333355128}},{"attributes":{"OBJECTID":349,"name":"The Point","source":" Captain Segulls Fishing Charts 2007"},"geometry":{"x":-74.8391666664307,"y":35.54766666701753}},{"attributes":{"OBJECTID":350,"name":"The Point","source":" Captain Segulls Fishing Charts 2007"},"geometry":{"x":-74.8391666664307,"y":35.54766666701753}},{"attributes":{"OBJECTID":351,"name":"The Point","source":" Captain Segulls Fishing Charts 2007"},"geometry":{"x":-74.8391666664307,"y":35.54766666701753}},{"attributes":{"OBJECTID":352,"name":"Bad Rock","source":" Captain Segulls Fishing Charts 2007"},"geometry":{"x":-75.29833333379285,"y":35.556666666369054}},{"attributes":{"OBJECTID":353,"name":"Bad Rock","source":" Captain Segulls Fishing Charts 2007"},"geometry":{"x":-75.29833333379285,"y":35.556666666369054}},{"attributes":{"OBJECTID":354,"name":"Bad Rock","source":" Captain Segulls Fishing Charts 2007"},"geometry":{"x":-75.29833333379285,"y":35.556666666369054}},{"attributes":{"OBJECTID":355,"name":"Wimble Shoals","source":"Various sources, reference metadata"},"geometry":{"x":-75.41669999991848,"y":35.566700000543115}},{"attributes":{"OBJECTID":356,"name":"Wimble Shoals","source":"Various sources, reference metadata"},"geometry":{"x":-75.41669999991848,"y":35.566700000543115}},{"attributes":{"OBJECTID":357,"name":"Wimble Shoals","source":"Various sources, reference metadata"},"geometry":{"x":-75.41669999991848,"y":35.566700000543115}},{"attributes":{"OBJECTID":358,"name":"The Point","source":"Coastal Guide. 2007; NCDMF. 2007b"},"geometry":{"x":-74.86670000024456,"y":35.566700000543115}},{"attributes":{"OBJECTID":359,"name":"The Point","source":"Coastal Guide. 2007; NCDMF. 2007b"},"geometry":{"x":-74.86670000024456,"y":35.566700000543115}},{"attributes":{"OBJECTID":360,"name":"The Point","source":"Coastal Guide. 2007; NCDMF. 2007b"},"geometry":{"x":-74.86670000024456,"y":35.566700000543115}},{"attributes":{"OBJECTID":361,"name":"The Point","source":"Various sources, reference metadata"},"geometry":{"x":-74.91669999988827,"y":35.66670000001534}},{"attributes":{"OBJECTID":362,"name":"The Point","source":"Various sources, reference metadata"},"geometry":{"x":-74.91669999988827,"y":35.66670000001534}},{"attributes":{"OBJECTID":363,"name":"The Point","source":"Various sources, reference metadata"},"geometry":{"x":-74.91669999988827,"y":35.66670000001534}},{"attributes":{"OBJECTID":364,"name":"U-85","source":" Captain Segulls Fishing Charts 2007"},"geometry":{"x":-75.28293333341752,"y":35.88685000001928}},{"attributes":{"OBJECTID":365,"name":"U-85","source":" Captain Segulls Fishing Charts 2007"},"geometry":{"x":-75.28293333341752,"y":35.88685000001928}},{"attributes":{"OBJECTID":366,"name":"U-85","source":" Captain Segulls Fishing Charts 2007"},"geometry":{"x":-75.28293333341752,"y":35.88685000001928}},{"attributes":{"OBJECTID":367,"name":"486 Hump","source":" Captain Segulls Fishing Charts 2007"},"geometry":{"x":-74.72666666655867,"y":35.93733333345645}},{"attributes":{"OBJECTID":368,"name":"486 Hump","source":" Captain Segulls Fishing Charts 2007"},"geometry":{"x":-74.72666666655867,"y":35.93733333345645}},{"attributes":{"OBJECTID":369,"name":"486 Hump","source":" Captain Segulls Fishing Charts 2007"},"geometry":{"x":-74.72666666655867,"y":35.93733333345645}},{"attributes":{"OBJECTID":370,"name":" ","source":" Captain Segulls Fishing Charts 2007"},"geometry":{"x":-75.34499999982755,"y":35.967499999581435}},{"attributes":{"OBJECTID":371,"name":" ","source":" Captain Segulls Fishing Charts 2007"},"geometry":{"x":-75.34499999982755,"y":35.967499999581435}},{"attributes":{"OBJECTID":372,"name":" ","source":" Captain Segulls Fishing Charts 2007"},"geometry":{"x":-75.34499999982755,"y":35.967499999581435}},{"attributes":{"OBJECTID":373,"name":"TRIPLE ZEROS","source":" Captain Segulls Fishing Charts 2007"},"geometry":{"x":-74.7833333334204,"y":36.249999999295795}},{"attributes":{"OBJECTID":374,"name":"TRIPLE ZEROS","source":" Captain Segulls Fishing Charts 2007"},"geometry":{"x":-74.7833333334204,"y":36.249999999295795}},{"attributes":{"OBJECTID":375,"name":"TRIPLE ZEROS","source":" Captain Segulls Fishing Charts 2007"},"geometry":{"x":-74.7833333334204,"y":36.249999999295795}},{"attributes":{"OBJECTID":376,"name":"20 FM LUMP","source":" Captain Segulls Fishing Charts 2007"},"geometry":{"x":-74.94583333293613,"y":36.26666666655071}},{"attributes":{"OBJECTID":377,"name":"20 FM LUMP","source":" Captain Segulls Fishing Charts 2007"},"geometry":{"x":-74.94583333293613,"y":36.26666666655071}},{"attributes":{"OBJECTID":378,"name":"20 FM LUMP","source":" Captain Segulls Fishing Charts 2007"},"geometry":{"x":-74.94583333293613,"y":36.26666666655071}},{"attributes":{"OBJECTID":379,"name":"BUARQUE","source":" Captain Segulls Fishing Charts 2007"},"geometry":{"x":-75.0495333329787,"y":36.300183333692715}},{"attributes":{"OBJECTID":380,"name":"BUARQUE","source":" Captain Segulls Fishing Charts 2007"},"geometry":{"x":-75.0495333329787,"y":36.300183333692715}},{"attributes":{"OBJECTID":381,"name":"BUARQUE","source":" Captain Segulls Fishing Charts 2007"},"geometry":{"x":-75.0495333329787,"y":36.300183333692715}},{"attributes":{"OBJECTID":382,"name":" ","source":" Captain Segulls Fishing Charts 2007"},"geometry":{"x":-74.95415000051523,"y":36.381183333258974}},{"attributes":{"OBJECTID":383,"name":" ","source":" Captain Segulls Fishing Charts 2007"},"geometry":{"x":-74.95415000051523,"y":36.381183333258974}},{"attributes":{"OBJECTID":384,"name":" ","source":" Captain Segulls Fishing Charts 2007"},"geometry":{"x":-74.95415000051523,"y":36.381183333258974}},{"attributes":{"OBJECTID":385,"name":"THE ELEVENS","source":" Captain Segulls Fishing Charts 2007"},"geometry":{"x":-75.29166666657484,"y":36.55000000005087}},{"attributes":{"OBJECTID":386,"name":"THE ELEVENS","source":" Captain Segulls Fishing Charts 2007"},"geometry":{"x":-75.29166666657484,"y":36.55000000005087}},{"attributes":{"OBJECTID":387,"name":"THE ELEVENS","source":" Captain Segulls Fishing Charts 2007"},"geometry":{"x":-75.29166666657484,"y":36.55000000005087}}]}